{
    "B01NCUSC7V": "2026-06-28T16:06:08.643259",
    "B0H1RGGF7D": "2026-06-28T19:10:43.424034",
    "B09Q97DWWJ": "2026-06-28T21:58:35.709372",
    "B00J9FM3TI": "2026-06-29T02:52:41.969196",
    "B0BWFJL62B": "2026-06-29T07:26:04.192835",
    "B08VK9N4BP": "2026-06-29T13:01:34.546103",
    "B0CV7QZF1S": "2026-06-29T17:32:14.877997",
    "B0B5RVR9BL": "2026-06-29T19:49:35.038049",
    "B082N3CB8G": "2026-06-29T22:06:33.178044",
    "B0CYM1KYW6": "2026-06-30T02:46:53.542618",
    "B0D7ZV3H7L": "2026-06-30T06:52:52.841651",
    "B099K1D44C": "2026-06-30T11:41:29.623722",
    "B09ZFKTSK1": "2026-06-30T14:06:54.754714",
    "_ultimas_categorias": [
        "Cremas bebe",
        "Baneras",
        "Juguetes",
        "Biberones"
    ],
    "_ultimos_titulos": [
        "Fisher-Price Laugh & Learn Perrito con Smart Stages Peluche musical de aprendizaje con Smart Stages ...",
        "Chicco PhysioForma Chupete Reci\u00e9n Nacido 0-2 Meses, Chupete Beb\u00e9 0 Meses de Silicona, Chupetes 0-6 M...",
        "Sophie la Girafe - Set GCF Giraffe Conservation - Desde el Nacimiento",
        "Fisher-Price Bloques Infantiles, Juguete para beb\u00e9 +6 Meses, Diez Bloques de Colores para ordenar, a..."
    ],
    "_categorias_semanales": {
        "Camaras seguridad": "2026-06-27T16:01:02.766836",
        "Chupetes": "2026-06-29T17:32:14.878368",
        "Tronas": "2026-06-28T19:10:43.424359",
        "Vajilla bebe": "2026-06-28T02:52:10.733854"
    }
}